ruamel.appconfig-0.5.4-py2.7-nspkg.pth
ruamel/appconfig/__init__.py
ruamel/appconfig/__main__.py
ruamel.appconfig-0.5.4.dist-info/DESCRIPTION.rst
ruamel.appconfig-0.5.4.dist-info/LICENSE.txt
ruamel.appconfig-0.5.4.dist-info/METADATA
ruamel.appconfig-0.5.4.dist-info/RECORD
ruamel.appconfig-0.5.4.dist-info/WHEEL
ruamel.appconfig-0.5.4.dist-info/metadata.json
ruamel.appconfig-0.5.4.dist-info/namespace_packages.txt
ruamel.appconfig-0.5.4.dist-info/top_level.txt
