Metadata-Version: 1.1
Name: ruamel.appconfig
Version: 0.5.4
Summary: create and read configuration dir/file, set argparse (sub)parser defaults from config
Home-page: https://bitbucket.org/ruamel/appconfig
Author: Anthon van der Neut
Author-email: a.van.der.neut@ruamel.eu
License: MIT license
Platform: UNKNOWN
Classifier: Development Status :: 4 - Beta
Classifier: Intended Audience :: Developers
Classifier: License :: OSI Approved :: MIT License
Classifier: Operating System :: OS Independent
Classifier: Programming Language :: Python
